nvidia/srl/_usd/__init__.py
nvidia/srl/_usd/py.typed
nvidia/srl/usd/__init__.py
nvidia/srl/usd/prim_helper.py
nvidia/srl/usd/py.typed
nvidia/srl/usd/types_helper.py
nvidia/srl/usd/world_structure.py
nvidia_srl_usd-2.0.0.dist-info/licenses/LICENSE
nvidia_srl_usd-2.0.0.dist-info/METADATA
nvidia_srl_usd-2.0.0.dist-info/WHEEL
nvidia_srl_usd-2.0.0.dist-info/top_level.txt
nvidia_srl_usd-2.0.0.dist-info/RECORD
