Metadata-Version: 2.4
Name: nvidia-srl-usd
Version: 2.0.0
Summary: SRL Python USD utils
Author: NVIDIA Seattle Robotics Lab
License-Expression: Apache-2.0
Project-URL: Homepage, https://gitlab-master.nvidia.com/srl/py/usd/-/blob/main/README.md
Project-URL: Documentation, https://srl.gitlab-master-pages.nvidia.com/py/usd
Project-URL: Repository, https://gitlab-master.nvidia.com/srl/py/usd
Project-URL: Issues, https://gitlab-master.nvidia.com/srl/py/usd/-/issues
Project-URL: Changelog, https://gitlab-master.nvidia.com/srl/py/usd/-/blob/main/CHANGELOG.md
Keywords: docker
Platform: any
Classifier: Operating System :: OS Independent
Classifier: Intended Audience :: Developers
Classifier: Natural Language :: English
Classifier: Programming Language :: Python :: 3
Classifier: Framework :: Robot Framework :: Library
Requires-Python: >=3.7
License-File: LICENSE
Requires-Dist: numpy<2.0.0,>=1.21.5
Requires-Dist: nvidia-srl-base<2.0.0,>=1.1.0
Requires-Dist: nvidia-srl-math<2.0.0,>=1.0.0
Requires-Dist: setuptools-scm<9.0.0,>=8.0.0; python_version >= "3.8"
Requires-Dist: setuptools-scm<8.0,>=6.0; python_version == "3.7"
Requires-Dist: tqdm<5.0.0,>=4.63.0
Requires-Dist: usd-core<26.0,>=25.2.post1; python_version >= "3.11"
Requires-Dist: usd-core<24.0,>=21.11; python_version >= "3.9" and python_version < "3.11"
Provides-Extra: ci
Requires-Dist: open3d==0.19.0; python_version >= "3.11" and extra == "ci"
Requires-Dist: open3d==0.17.0; (python_version >= "3.9" and python_version < "3.11") and extra == "ci"
Requires-Dist: open3d==0.13.0; python_version < "3.9" and extra == "ci"
Requires-Dist: tqdm-stubs==0.2.1; extra == "ci"
Requires-Dist: usd-core==25.2.post1; python_version >= "3.11" and extra == "ci"
Requires-Dist: usd-core==23.8; (python_version >= "3.9" and python_version < "3.11") and extra == "ci"
Requires-Dist: black==25.1.0; extra == "ci"
Requires-Dist: flake8==7.2.0; extra == "ci"
Requires-Dist: flake8-copyright==0.2.4; extra == "ci"
Requires-Dist: flake8-docstrings==1.7.0; extra == "ci"
Requires-Dist: flake8-isort==6.1.2; extra == "ci"
Requires-Dist: flake8-rst-docstrings==0.3.1; extra == "ci"
Requires-Dist: flake8-pyproject==1.2.3; extra == "ci"
Requires-Dist: isort==5.12.0; extra == "ci"
Requires-Dist: mypy==1.16.0; extra == "ci"
Requires-Dist: pep8-naming==0.15.1; extra == "ci"
Requires-Dist: pytest==8.4.0; extra == "ci"
Requires-Dist: pytest-cov==6.2.1; extra == "ci"
Requires-Dist: pytest-xdist==3.7.0; extra == "ci"
Requires-Dist: docutils==0.21.2; extra == "ci"
Requires-Dist: graphviz==0.20.3; extra == "ci"
Requires-Dist: sphinx==8.1.3; extra == "ci"
Requires-Dist: sphinx-rtd-theme==3.0.2; extra == "ci"
Requires-Dist: sphinx-copybutton==0.5.2; extra == "ci"
Requires-Dist: build==1.2.2.post1; extra == "ci"
Requires-Dist: twine==6.1.0; extra == "ci"
Requires-Dist: anybadge==1.16.0; extra == "ci"
Provides-Extra: dev
Requires-Dist: ipdb; extra == "dev"
Requires-Dist: ipython; extra == "dev"
Requires-Dist: nvidia-srl-dock; extra == "dev"
Dynamic: license-file
